pywedge/__init__.py
pywedge/pywedge.py
pywedge-0.5.1.8.dist-info/LICENSE.txt
pywedge-0.5.1.8.dist-info/METADATA
pywedge-0.5.1.8.dist-info/WHEEL
pywedge-0.5.1.8.dist-info/top_level.txt
pywedge-0.5.1.8.dist-info/RECORD
