Metadata-Version: 2.1
Name: pywedge
Version: 0.5.1.8
Summary: Makes Interactive Charts, Interactive Baseline, Interactive Hyperparameter Tuning & Predictions
Home-page: https://github.com/taknev83/pywedge
Author: Venkatesh Rengarajan Muthu
Author-email: taknev83@gmail.com
License: MIT
Platform: UNKNOWN
Classifier: Programming Language :: Python :: 3
Classifier: Development Status :: 4 - Beta
Classifier: License :: OSI Approved :: MIT License
Classifier: Operating System :: OS Independent
Requires-Dist: xgboost
Requires-Dist: pandas
Requires-Dist: catboost (>0.24)
Requires-Dist: numpy
Requires-Dist: scikit-learn
Requires-Dist: imbalanced-learn
Requires-Dist: plotly
Requires-Dist: ipywidgets
Requires-Dist: tqdm
